simpleGrid/__init__.py
simpleGrid/main.py
simple_grid-0.1.1.dist-info/LICENSE
simple_grid-0.1.1.dist-info/METADATA
simple_grid-0.1.1.dist-info/WHEEL
simple_grid-0.1.1.dist-info/top_level.txt
simple_grid-0.1.1.dist-info/RECORD
