Metadata-Version: 2.1
Name: simple-grid
Version: 0.1.1
Summary: This Package creates a simple grid to show some data
Home-page: UNKNOWN
Author: domx4q
Author-email: ev3dom@gmx.de
License: UNKNOWN
Project-URL: Cloudster, https://cloudster.online
Platform: UNKNOWN
Classifier: Programming Language :: Python :: 3
Classifier: License :: OSI Approved :: MIT License
Classifier: Operating System :: OS Independent
Requires-Python: >=3.6
License-File: LICENSE
